geomfum/__init__.py
geomfum/_registry.py
geomfum/_utils.py
geomfum/basis.py
geomfum/convert.py
geomfum/forward_functional_map.py
geomfum/functional_map.py
geomfum/io.py
geomfum/laplacian.py
geomfum/linalg.py
geomfum/neural_adjoint_map.py
geomfum/operator.py
geomfum/plot.py
geomfum/refine.py
geomfum/sample.py
geomfum/dataset/__init__.py
geomfum/dataset/_defaults.py
geomfum/dataset/_utils.py
geomfum/dataset/notebook.py
geomfum/dataset/torch.py
geomfum/descriptor/__init__.py
geomfum/descriptor/_base.py
geomfum/descriptor/learned.py
geomfum/descriptor/pipeline.py
geomfum/descriptor/spectral.py
geomfum/learning/losses.py
geomfum/learning/models.py
geomfum/learning/trainer.py
geomfum/metric/__init__.py
geomfum/metric/_base.py
geomfum/metric/mesh.py
geomfum/metric/point_cloud.py
geomfum/numerics/__init__.py
geomfum/numerics/eig.py
geomfum/numerics/graph.py
geomfum/numerics/optimization.py
geomfum/shape/__init__.py
geomfum/shape/_base.py
geomfum/shape/hierarchical.py
geomfum/shape/mesh.py
geomfum/shape/point_cloud.py
geomfum/shape/shape_utils.py
geomfum/shape/convert/__init__.py
geomfum/shape/convert/_plotly.py
geomfum/shape/convert/_pyvista.py
geomfum/wrap/__init__.py
geomfum/wrap/diffusionnet.py
geomfum/wrap/igl.py
geomfum/wrap/plotly.py
geomfum/wrap/pointnet.py
geomfum/wrap/polyscope.py
geomfum/wrap/pot.py
geomfum/wrap/pp3d.py
geomfum/wrap/pyfm.py
geomfum/wrap/pymeshlab.py
geomfum/wrap/pyrmt.py
geomfum/wrap/pyvista.py
geomfum/wrap/robust.py
geomfum/wrap/transformer.py
geomfum-1.0.0.dist-info/licenses/LICENSE.md
geomfum-1.0.0.dist-info/METADATA
geomfum-1.0.0.dist-info/WHEEL
geomfum-1.0.0.dist-info/top_level.txt
geomfum-1.0.0.dist-info/RECORD
