Metadata-Version: 2.4
Name: geomfum
Version: 1.0.0
Summary: Geometry processing with functional maps.
Author-email: Giulio Viganò <g.vigano36@campus.unimib.it>, Giorgio Longari <giorgio.longari@unimib.it>, "Luís F. Pereira" <luisfpereira@ucsb.edu>, Nina Miolane <ninamiolane@ucsb.edu>, Simone Melzi <simone.melzi@unimib.it>
License: MIT License
Project-URL: repository, http://github.com/3diglab/geomfum
Classifier: License :: OSI Approved :: MIT License
Classifier: Development Status :: 2 - Pre-Alpha
Classifier: Intended Audience :: Science/Research
Classifier: Topic :: Scientific/Engineering
Classifier: Topic :: Scientific/Engineering :: Mathematics
Classifier: Programming Language :: Python :: 3
Requires-Python: >=3.9
License-File: LICENSE.md
Requires-Dist: numpy
Requires-Dist: scipy
Requires-Dist: scikit-learn
Requires-Dist: meshio
Requires-Dist: pyfmaps
Requires-Dist: torch
Requires-Dist: gsops
Provides-Extra: lapl
Requires-Dist: robust-laplacian; extra == "lapl"
Requires-Dist: libigl; extra == "lapl"
Provides-Extra: metric
Requires-Dist: networkx; extra == "metric"
Requires-Dist: potpourri3d; extra == "metric"
Provides-Extra: sampling
Requires-Dist: pymeshlab; extra == "sampling"
Provides-Extra: rematching
Provides-Extra: sinkhorn
Requires-Dist: POT; extra == "sinkhorn"
Provides-Extra: opt
Requires-Dist: geomfum[lapl,metric,rematching,sampling,sinkhorn]; extra == "opt"
Provides-Extra: fun
Provides-Extra: test-scripts
Requires-Dist: nbformat; extra == "test-scripts"
Requires-Dist: nbconvert; extra == "test-scripts"
Requires-Dist: ipykernel; extra == "test-scripts"
Requires-Dist: ipython; extra == "test-scripts"
Requires-Dist: pyvista; extra == "test-scripts"
Requires-Dist: plotly; extra == "test-scripts"
Provides-Extra: test
Requires-Dist: pytest; extra == "test"
Requires-Dist: geomfum[opt,plotting-all,test-scripts]; extra == "test"
Provides-Extra: plotly
Requires-Dist: plotly; extra == "plotly"
Requires-Dist: nbformat; extra == "plotly"
Provides-Extra: pyvista
Requires-Dist: pyvista; extra == "pyvista"
Requires-Dist: trame; extra == "pyvista"
Provides-Extra: polyscope
Requires-Dist: polyscope; extra == "polyscope"
Provides-Extra: plotting-all
Requires-Dist: geomfum[plotly,polyscope,pyvista]; extra == "plotting-all"
Dynamic: license-file
